polars_trading-0.2.0.dist-info/METADATA
polars_trading-0.2.0.dist-info/WHEEL
polars_trading/__init__.py
polars_trading/_internal.abi3.so
polars_trading/_internal.pyi
polars_trading/_testing/__init__.py
polars_trading/_testing/data.py
polars_trading/_testing/features.py
polars_trading/_testing/labels.py
polars_trading/_utils.py
polars_trading/bars.py
polars_trading/config.py
polars_trading/features/__init__.py
polars_trading/features/frac_diff.py
polars_trading/labels/__init__.py
polars_trading/labels/dynamic_labels.py
polars_trading/labels/labels.py
polars_trading/options/__init__.py
polars_trading/options/black_scholes.py
polars_trading/py.typed
polars_trading/typing.py
polars_trading-0.2.0.dist-info/RECORD
