Metadata-Version: 2.4
Name: polars-trading
Version: 0.2.0
Classifier: Programming Language :: Rust
Classifier: Programming Language :: Python :: Implementation :: CPython
Classifier: Programming Language :: Python :: Implementation :: PyPy
Requires-Dist: polars[plot]>=1.13
Requires-Python: >=3.10
